pennant/__init__.py
pennant/pennant.py
pennant-0.1.5.dist-info/LICENSE
pennant-0.1.5.dist-info/METADATA
pennant-0.1.5.dist-info/WHEEL
pennant-0.1.5.dist-info/top_level.txt
pennant-0.1.5.dist-info/RECORD
