Metadata-Version: 2.1
Name: pennant
Version: 0.1.5
Summary: A high-spirited feature-flagging library for Python.
Home-page: https://github.com/dluman/pennant
License: UNKNOWN
Platform: UNKNOWN
